hypixel_data/__init__.py
hypixel_data/achievements.py
hypixel.py_data-1.0.2.dist-info/LICENSE
hypixel.py_data-1.0.2.dist-info/METADATA
hypixel.py_data-1.0.2.dist-info/WHEEL
hypixel.py_data-1.0.2.dist-info/top_level.txt
hypixel.py_data-1.0.2.dist-info/RECORD
